[{"id":698,"round":1,"grandPrixId":"australia","date":"2003-03-09","results":[{"driverId":"david-coulthard","position":1,"points":10},{"driverId":"juan-pablo-montoya","position":2,"points":8},{"driverId":"kimi-raikkonen","position":3,"points":6},{"driverId":"michael-schumacher","position":4,"points":5},{"driverId":"jarno-trulli","position":5,"points":4},{"driverId":"heinz-harald-frentzen","position":6,"points":3},{"driverId":"fernando-alonso","position":7,"points":2},{"driverId":"ralf-schumacher","position":8,"points":1},{"driverId":"jacques-villeneuve","position":9,"points":0},{"driverId":"jenson-button","position":10,"points":0},{"driverId":"jos-verstappen","position":11,"points":0},{"driverId":"giancarlo-fisichella","position":12,"points":0},{"driverId":"antonio-pizzonia","position":13,"points":0}]},{"id":699,"round":2,"grandPrixId":"malaysia","date":"2003-03-23","results":[{"driverId":"kimi-raikkonen","position":1,"points":10},{"driverId":"rubens-barrichello","position":2,"points":8},{"driverId":"fernando-alonso","position":3,"points":6},{"driverId":"ralf-schumacher","position":4,"points":5},{"driverId":"jarno-trulli","position":5,"points":4},{"driverId":"michael-schumacher","position":6,"points":3},{"driverId":"jenson-button","position":7,"points":2},{"driverId":"nick-heidfeld","position":8,"points":1},{"driverId":"heinz-harald-frentzen","position":9,"points":0},{"driverId":"ralph-firman","position":10,"points":0},{"driverId":"cristiano-da-matta","position":11,"points":0},{"driverId":"juan-pablo-montoya","position":12,"points":0},{"driverId":"jos-verstappen","position":13,"points":0}]},{"id":700,"round":3,"grandPrixId":"brazil","date":"2003-04-06","results":[{"driverId":"giancarlo-fisichella","position":1,"points":10},{"driverId":"kimi-raikkonen","position":2,"points":8},{"driverId":"fernando-alonso","position":3,"points":6},{"driverId":"david-coulthard","position":4,"points":5},{"driverId":"heinz-harald-frentzen","position":5,"points":4},{"driverId":"jacques-villeneuve","position":6,"points":3},{"driverId":"ralf-schumacher","position":7,"points":2},{"driverId":"jarno-trulli","position":8,"points":1},{"driverId":"mark-webber","position":9,"points":0},{"driverId":"cristiano-da-matta","position":10,"points":0}]},{"id":701,"round":4,"grandPrixId":"san-marino","date":"2003-04-20","results":[{"driverId":"michael-schumacher","position":1,"points":10},{"driverId":"kimi-raikkonen","position":2,"points":8},{"driverId":"rubens-barrichello","position":3,"points":6},{"driverId":"ralf-schumacher","position":4,"points":5},{"driverId":"david-coulthard","position":5,"points":4},{"driverId":"fernando-alonso","position":6,"points":3},{"driverId":"juan-pablo-montoya","position":7,"points":2},{"driverId":"jenson-button","position":8,"points":1},{"driverId":"olivier-panis","position":9,"points":0},{"driverId":"nick-heidfeld","position":10,"points":0},{"driverId":"heinz-harald-frentzen","position":11,"points":0},{"driverId":"cristiano-da-matta","position":12,"points":0},{"driverId":"jarno-trulli","position":13,"points":0},{"driverId":"antonio-pizzonia","position":14,"points":0},{"driverId":"giancarlo-fisichella","position":15,"points":0}]},{"id":702,"round":5,"grandPrixId":"spain","date":"2003-05-04","results":[{"driverId":"michael-schumacher","position":1,"points":10},{"driverId":"fernando-alonso","position":2,"points":8},{"driverId":"rubens-barrichello","position":3,"points":6},{"driverId":"juan-pablo-montoya","position":4,"points":5},{"driverId":"ralf-schumacher","position":5,"points":4},{"driverId":"cristiano-da-matta","position":6,"points":3},{"driverId":"mark-webber","position":7,"points":2},{"driverId":"ralph-firman","position":8,"points":1},{"driverId":"jenson-button","position":9,"points":0},{"driverId":"nick-heidfeld","position":10,"points":0},{"driverId":"justin-wilson","position":11,"points":0},{"driverId":"jos-verstappen","position":12,"points":0}]},{"id":703,"round":6,"grandPrixId":"austria","date":"2003-05-18","results":[{"driverId":"michael-schumacher","position":1,"points":10},{"driverId":"kimi-raikkonen","position":2,"points":8},{"driverId":"rubens-barrichello","position":3,"points":6},{"driverId":"jenson-button","position":4,"points":5},{"driverId":"david-coulthard","position":5,"points":4},{"driverId":"ralf-schumacher","position":6,"points":3},{"driverId":"mark-webber","position":7,"points":2},{"driverId":"jarno-trulli","position":8,"points":1},{"driverId":"antonio-pizzonia","position":9,"points":0},{"driverId":"cristiano-da-matta","position":10,"points":0},{"driverId":"ralph-firman","position":11,"points":0},{"driverId":"jacques-villeneuve","position":12,"points":0},{"driverId":"justin-wilson","position":13,"points":0}]},{"id":704,"round":7,"grandPrixId":"monaco","date":"2003-06-01","results":[{"driverId":"juan-pablo-montoya","position":1,"points":10},{"driverId":"kimi-raikkonen","position":2,"points":8},{"driverId":"michael-schumacher","position":3,"points":6},{"driverId":"ralf-schumacher","position":4,"points":5},{"driverId":"fernando-alonso","position":5,"points":4},{"driverId":"jarno-trulli","position":6,"points":3},{"driverId":"david-coulthard","position":7,"points":2},{"driverId":"rubens-barrichello","position":8,"points":1},{"driverId":"cristiano-da-matta","position":9,"points":0},{"driverId":"giancarlo-fisichella","position":10,"points":0},{"driverId":"nick-heidfeld","position":11,"points":0},{"driverId":"ralph-firman","position":12,"points":0},{"driverId":"olivier-panis","position":13,"points":0}]},{"id":705,"round":8,"grandPrixId":"canada","date":"2003-06-15","results":[{"driverId":"michael-schumacher","position":1,"points":10},{"driverId":"ralf-schumacher","position":2,"points":8},{"driverId":"juan-pablo-montoya","position":3,"points":6},{"driverId":"fernando-alonso","position":4,"points":5},{"driverId":"rubens-barrichello","position":5,"points":4},{"driverId":"kimi-raikkonen","position":6,"points":3},{"driverId":"mark-webber","position":7,"points":2},{"driverId":"olivier-panis","position":8,"points":1},{"driverId":"jos-verstappen","position":9,"points":0},{"driverId":"antonio-pizzonia","position":10,"points":0},{"driverId":"cristiano-da-matta","position":11,"points":0}]},{"id":706,"round":9,"grandPrixId":"europe","date":"2003-06-29","results":[{"driverId":"ralf-schumacher","position":1,"points":10},{"driverId":"juan-pablo-montoya","position":2,"points":8},{"driverId":"rubens-barrichello","position":3,"points":6},{"driverId":"fernando-alonso","position":4,"points":5},{"driverId":"michael-schumacher","position":5,"points":4},{"driverId":"mark-webber","position":6,"points":3},{"driverId":"jenson-button","position":7,"points":2},{"driverId":"nick-heidfeld","position":8,"points":1},{"driverId":"heinz-harald-frentzen","position":9,"points":0},{"driverId":"antonio-pizzonia","position":10,"points":0},{"driverId":"ralph-firman","position":11,"points":0},{"driverId":"giancarlo-fisichella","position":12,"points":0},{"driverId":"justin-wilson","position":13,"points":0},{"driverId":"jos-verstappen","position":14,"points":0},{"driverId":"david-coulthard","position":15,"points":0}]},{"id":707,"round":10,"grandPrixId":"france","date":"2003-07-06","results":[{"driverId":"ralf-schumacher","position":1,"points":10},{"driverId":"juan-pablo-montoya","position":2,"points":8},{"driverId":"michael-schumacher","position":3,"points":6},{"driverId":"kimi-raikkonen","position":4,"points":5},{"driverId":"david-coulthard","position":5,"points":4},{"driverId":"mark-webber","position":6,"points":3},{"driverId":"rubens-barrichello","position":7,"points":2},{"driverId":"olivier-panis","position":8,"points":1},{"driverId":"jacques-villeneuve","position":9,"points":0},{"driverId":"antonio-pizzonia","position":10,"points":0},{"driverId":"cristiano-da-matta","position":11,"points":0},{"driverId":"heinz-harald-frentzen","position":12,"points":0},{"driverId":"nick-heidfeld","position":13,"points":0},{"driverId":"justin-wilson","position":14,"points":0},{"driverId":"ralph-firman","position":15,"points":0},{"driverId":"jos-verstappen","position":16,"points":0}]},{"id":708,"round":11,"grandPrixId":"great-britain","date":"2003-07-20","results":[{"driverId":"rubens-barrichello","position":1,"points":10},{"driverId":"juan-pablo-montoya","position":2,"points":8},{"driverId":"kimi-raikkonen","position":3,"points":6},{"driverId":"michael-schumacher","position":4,"points":5},{"driverId":"david-coulthard","position":5,"points":4},{"driverId":"jarno-trulli","position":6,"points":3},{"driverId":"cristiano-da-matta","position":7,"points":2},{"driverId":"jenson-button","position":8,"points":1},{"driverId":"ralf-schumacher","position":9,"points":0},{"driverId":"jacques-villeneuve","position":10,"points":0},{"driverId":"olivier-panis","position":11,"points":0},{"driverId":"heinz-harald-frentzen","position":12,"points":0},{"driverId":"ralph-firman","position":13,"points":0},{"driverId":"mark-webber","position":14,"points":0},{"driverId":"jos-verstappen","position":15,"points":0},{"driverId":"justin-wilson","position":16,"points":0},{"driverId":"nick-heidfeld","position":17,"points":0}]},{"id":709,"round":12,"grandPrixId":"germany","date":"2003-08-03","results":[{"driverId":"juan-pablo-montoya","position":1,"points":10},{"driverId":"david-coulthard","position":2,"points":8},{"driverId":"jarno-trulli","position":3,"points":6},{"driverId":"fernando-alonso","position":4,"points":5},{"driverId":"olivier-panis","position":5,"points":4},{"driverId":"cristiano-da-matta","position":6,"points":3},{"driverId":"michael-schumacher","position":7,"points":2},{"driverId":"jenson-button","position":8,"points":1},{"driverId":"jacques-villeneuve","position":9,"points":0},{"driverId":"nick-heidfeld","position":10,"points":0},{"driverId":"mark-webber","position":11,"points":0},{"driverId":"nicolas-kiesa","position":12,"points":0},{"driverId":"giancarlo-fisichella","position":13,"points":0}]},{"id":710,"round":13,"grandPrixId":"hungary","date":"2003-08-24","results":[{"driverId":"fernando-alonso","position":1,"points":10},{"driverId":"kimi-raikkonen","position":2,"points":8},{"driverId":"juan-pablo-montoya","position":3,"points":6},{"driverId":"ralf-schumacher","position":4,"points":5},{"driverId":"david-coulthard","position":5,"points":4},{"driverId":"mark-webber","position":6,"points":3},{"driverId":"jarno-trulli","position":7,"points":2},{"driverId":"michael-schumacher","position":8,"points":1},{"driverId":"nick-heidfeld","position":9,"points":0},{"driverId":"jenson-button","position":10,"points":0},{"driverId":"cristiano-da-matta","position":11,"points":0},{"driverId":"jos-verstappen","position":12,"points":0},{"driverId":"nicolas-kiesa","position":13,"points":0}]},{"id":711,"round":14,"grandPrixId":"italy","date":"2003-09-14","results":[{"driverId":"michael-schumacher","position":1,"points":10},{"driverId":"juan-pablo-montoya","position":2,"points":8},{"driverId":"rubens-barrichello","position":3,"points":6},{"driverId":"kimi-raikkonen","position":4,"points":5},{"driverId":"marc-gene","position":5,"points":4},{"driverId":"jacques-villeneuve","position":6,"points":3},{"driverId":"mark-webber","position":7,"points":2},{"driverId":"fernando-alonso","position":8,"points":1},{"driverId":"nick-heidfeld","position":9,"points":0},{"driverId":"giancarlo-fisichella","position":10,"points":0},{"driverId":"zsolt-baumgartner","position":11,"points":0},{"driverId":"nicolas-kiesa","position":12,"points":0},{"driverId":"heinz-harald-frentzen","position":13,"points":0}]},{"id":712,"round":15,"grandPrixId":"united-states","date":"2003-09-28","results":[{"driverId":"michael-schumacher","position":1,"points":10},{"driverId":"kimi-raikkonen","position":2,"points":8},{"driverId":"heinz-harald-frentzen","position":3,"points":6},{"driverId":"jarno-trulli","position":4,"points":5},{"driverId":"nick-heidfeld","position":5,"points":4},{"driverId":"juan-pablo-montoya","position":6,"points":3},{"driverId":"giancarlo-fisichella","position":7,"points":2},{"driverId":"justin-wilson","position":8,"points":1},{"driverId":"cristiano-da-matta","position":9,"points":0},{"driverId":"jos-verstappen","position":10,"points":0},{"driverId":"nicolas-kiesa","position":11,"points":0}]},{"id":713,"round":16,"grandPrixId":"japan","date":"2003-10-12","results":[{"driverId":"rubens-barrichello","position":1,"points":10},{"driverId":"kimi-raikkonen","position":2,"points":8},{"driverId":"david-coulthard","position":3,"points":6},{"driverId":"jenson-button","position":4,"points":5},{"driverId":"jarno-trulli","position":5,"points":4},{"driverId":"takuma-sato","position":6,"points":3},{"driverId":"cristiano-da-matta","position":7,"points":2},{"driverId":"michael-schumacher","position":8,"points":1},{"driverId":"nick-heidfeld","position":9,"points":0},{"driverId":"olivier-panis","position":10,"points":0},{"driverId":"mark-webber","position":11,"points":0},{"driverId":"ralf-schumacher","position":12,"points":0},{"driverId":"justin-wilson","position":13,"points":0},{"driverId":"ralph-firman","position":14,"points":0},{"driverId":"jos-verstappen","position":15,"points":0},{"driverId":"nicolas-kiesa","position":16,"points":0}]}]